{
    "key": "group_5e71f38a79f93",
    "title": "Review",
    "fields": [
        {
            "key": "field_5e71f3957b2fa",
            "label": "Reviewer Name",
            "name": "reviewer_name",
            "aria-label": "",
            "type": "text",
            "instructions": "",
            "required": 0,
            "conditional_logic": 0,
            "wrapper": {
                "width": "",
                "class": "",
                "id": ""
            },
            "default_value": "",
            "placeholder": "",
            "prepend": "",
            "append": "",
            "maxlength": ""
        },
        {
            "key": "field_5e7203d7d3bf7",
            "label": "Reviewer Country",
            "name": "reviewer_country",
            "aria-label": "",
            "type": "text",
            "instructions": "",
            "required": 0,
            "conditional_logic": 0,
            "wrapper": {
                "width": "",
                "class": "",
                "id": ""
            },
            "choices": "",
            "default_value": "",
            "allow_null": 0,
            "multiple": 0,
            "ui": 0,
            "return_format": "value",
            "maxlength": "",
            "placeholder": "",
            "prepend": "",
            "append": ""
        },
        {
            "key": "field_5e71f4c035c9f",
            "label": "Reviewer Rating",
            "name": "reviewer_rating",
            "aria-label": "",
            "type": "select",
            "instructions": "",
            "required": 0,
            "conditional_logic": 0,
            "wrapper": {
                "width": "",
                "class": "",
                "id": ""
            },
            "choices": {
                "1": "1",
                "2": "2",
                "3": "3",
                "4": "4",
                "5": "5"
            },
            "default_value": false,
            "allow_null": 0,
            "multiple": 0,
            "ui": 0,
            "return_format": "value",
            "ajax": 0,
            "placeholder": ""
        },
        {
            "key": "field_5eb55635659a5",
            "label": "Reviewer Trip",
            "name": "reviewer_trip",
            "aria-label": "",
            "type": "post_object",
            "instructions": "",
            "required": 0,
            "conditional_logic": 0,
            "wrapper": {
                "width": "",
                "class": "",
                "id": ""
            },
            "post_type": [
                "trips"
            ],
            "taxonomy": "",
            "allow_null": 0,
            "multiple": 0,
            "return_format": "id",
            "ui": 1
        },
        {
            "key": "field_5f04220c31cbe",
            "label": "Reviewer Trip Photos",
            "name": "reviewer_trip_photos",
            "aria-label": "",
            "type": "gallery",
            "instructions": "",
            "required": 0,
            "conditional_logic": 0,
            "wrapper": {
                "width": "",
                "class": "",
                "id": ""
            },
            "min": "",
            "max": "",
            "insert": "append",
            "library": "all",
            "min_width": "",
            "min_height": "",
            "min_size": "",
            "max_width": "",
            "max_height": "",
            "max_size": "",
            "mime_types": "",
            "return_format": "array",
            "preview_size": "medium"
        }
    ],
    "location": [
        [
            {
                "param": "page_template",
                "operator": "==",
                "value": "trip-details.php"
            }
        ]
    ],
    "menu_order": 0,
    "position": "normal",
    "style": "default",
    "label_placement": "top",
    "instruction_placement": "label",
    "hide_on_screen": "",
    "active": true,
    "description": "",
    "show_in_rest": 0,
    "modified": 1672744051
}